gistqd-0.1.2.dist-info/METADATA
gistqd-0.1.2.dist-info/WHEEL
gistqd-0.1.2.dist-info/entry_points.txt
gistqd/__init__.py
gistqd/__main__.py
gistqd/backend/__init__.py
gistqd/backend/__main__.py
gistqd/backend/helpers/function_timer.py
gistqd/backend/models/image_pipeline.py
gistqd/backend/models/palette.py
gistqd/backend/processors/ordered_dithering.py
gistqd/backend/processors/palette_quantizer.py
gistqd/cli.py
gistqd/config.py
gistqd/default.toml
gistqd/palettes/catppuccin_frappe.json
gistqd/palettes/catppuccin_latte.json
gistqd/palettes/catppuccin_macchiato.json
gistqd/palettes/catppuccin_mocha.json
gistqd/palettes/dracula.json
gistqd/palettes/gruvbox.json
gistqd-0.1.2.dist-info/RECORD
