Metadata-Version: 2.1
Name: gistqd
Version: 0.1.2
Summary: A simple CLICK application to style images using palettes or just raw transformations
Author-Email: Anatoliy Dudar <gigsollt@gmail.com>
License: MIT
Requires-Python: >=3.13
Requires-Dist: numpy>=2.3.1
Requires-Dist: opencv-python>=4.11.0.86
Requires-Dist: pillow>=11.3.0
Requires-Dist: pygobject-stubs>=2.13.0
Requires-Dist: click>=8.2.1
Requires-Dist: platformdirs>=4.3.8
